pluscoder/__init__.py
pluscoder/__main__.py
pluscoder/__version__.py
pluscoder/commands.py
pluscoder/display_utils.py
pluscoder/exceptions.py
pluscoder/fs.py
pluscoder/io_utils.py
pluscoder/live_display.py
pluscoder/logs.py
pluscoder/main.py
pluscoder/message_utils.py
pluscoder/model.py
pluscoder/repo.py
pluscoder/repomap.py
pluscoder/setup.py
pluscoder/state_utils.py
pluscoder/tools.py
pluscoder/type.py
pluscoder/workflow.py
pluscoder/agents/__init__.py
pluscoder/agents/__main__.py
pluscoder/agents/base.py
pluscoder/agents/core.py
pluscoder/agents/orchestrator.py
pluscoder/agents/prompts.py
pluscoder/agents/stream_parser.py
pluscoder/agents/utils.py
pluscoder/agents/event/__init__.py
pluscoder/agents/event/base.py
pluscoder/agents/event/config.py
pluscoder/agents/event/event_handler/__init__.py
pluscoder/agents/event/event_handler/base.py
pluscoder/agents/event/event_handler/console_event_handler.py
pluscoder/agents/event/event_handler/git_event_handler.py
pluscoder/agents/output_handlers/__init__.py
pluscoder/agents/output_handlers/action_handlers.py
pluscoder/agents/output_handlers/tag_handlers.py
pluscoder/assets/__init__.py
pluscoder/assets/model_cost.json
pluscoder/assets/model_default.json
pluscoder/config/__init__.py
pluscoder/config/config.py
pluscoder/config/utils.py
pluscoder/search/__init__.py
pluscoder/search/engine.py
pluscoder/search/example.py
pluscoder/search/index_manager.py
pluscoder/search/models.py
pluscoder/search/storage.py
pluscoder/search/algorithms/__init__.py
pluscoder/search/chunking/__init__.py
pluscoder/search/embeddings/__init__.py
pluscoder/search/embeddings/models.py
pluscoder/search/embeddings/providers.py
pluscoder-0.1.2.dist-info/METADATA
pluscoder-0.1.2.dist-info/WHEEL
pluscoder-0.1.2.dist-info/entry_points.txt
pluscoder-0.1.2.dist-info/top_level.txt
pluscoder-0.1.2.dist-info/RECORD
